dominus/__init__.py
dominus/dominus_pb2.py
dominus/dominus_pb2_grpc.py
dominus_python_sdk-0.24.0.dist-info/METADATA
dominus_python_sdk-0.24.0.dist-info/WHEEL
dominus_python_sdk-0.24.0.dist-info/top_level.txt
dominus_python_sdk-0.24.0.dist-info/RECORD
